xtyping/__about__.py
xtyping/__init__.py
xtyping/__main__.py
xtyping/_all.py
xtyping/npt.py
xtyping/py.typed
xtyping/shed.py
xtyping-0.11.1.dist-info/WHEEL
xtyping-0.11.1.dist-info/METADATA
xtyping-0.11.1.dist-info/RECORD
