Metadata-Version: 2.3
Name: xtyping
Version: 0.11.1
Summary: xtyping = typing + typing_extensions
Keywords: dgpy,typed,types,typing
Author: jesse
Author-email: jesse <jesse@dgi.com>
Classifier: Development Status :: 5 - Production/Stable
Classifier: Intended Audience :: Developers
Classifier: License :: OSI Approved :: MIT License
Classifier: Programming Language :: Python
Classifier: Programming Language :: Python :: 3 :: Only
Classifier: Programming Language :: Python :: 3.11
Classifier: Programming Language :: Python :: 3.12
Classifier: Programming Language :: Python :: 3.13
Classifier: Programming Language :: Python :: 3.14
Classifier: Typing :: Typed
Requires-Dist: annotated-types>=0.7
Requires-Dist: typing-extensions>=4.12.2
Requires-Python: >=3.11, <4.0
